newsbinpro_client/__init__.py
newsbinpro_client/command.py
newsbinpro_client/downloadfileset.py
newsbinpro_client/downloadpartstatus.py
newsbinpro_client/filesdownloaditem.py
newsbinpro_client/filesfileset.py
newsbinpro_client/groupfileset.py
newsbinpro_client/groupofgroupstree.py
newsbinpro_client/listresponse.py
newsbinpro_client/newsbinproclient.py
newsbinpro_client/newsbinprostatus.py
newsbinpro_client/response.py
newsbinpro_client/statuscode.py
newsbinpro_client/wishfileset.py
newsbinpro_client-1.0.3.dist-info/LICENSE
newsbinpro_client-1.0.3.dist-info/METADATA
newsbinpro_client-1.0.3.dist-info/WHEEL
newsbinpro_client-1.0.3.dist-info/top_level.txt
newsbinpro_client-1.0.3.dist-info/RECORD
