Metadata-Version: 2.1
Name: newsbinpro_client
Version: 1.0.3
Summary: A client for the Newsbin Pro Usenet Downloader
Home-page: https://github.com/jonnybergdahl/Python-NewsbinPro-Client
Author: Jonny Bergdahl
Author-email: github@bergdahl.it
License: MIT
Classifier: Development Status :: 5 - Production/Stable
Classifier: Intended Audience :: Developers
Classifier: License :: OSI Approved :: MIT License
Classifier: Topic :: Home Automation
Classifier: Programming Language :: Python :: 3
Classifier: Programming Language :: Python :: 3.9
Classifier: Programming Language :: Python :: 3.10
Classifier: Programming Language :: Python :: 3.11
Classifier: Programming Language :: Python :: 3.12
License-File: LICENSE
